mnists/__init__.py
mnists/_emnist.py
mnists/_mnist.py
mnists/dataset.py
mnists/utils.py
mnists-0.4.1.dist-info/LICENSE
mnists-0.4.1.dist-info/METADATA
mnists-0.4.1.dist-info/WHEEL
mnists-0.4.1.dist-info/top_level.txt
mnists-0.4.1.dist-info/RECORD
