Metadata-Version: 2.1
Name: mnists
Version: 0.4.1
Summary: MNISTs: All MNIST-like datasets in one package
Author-email: Piotr Czarnik <ptr.czarnik@gmail.com>
Project-URL: Homepage, https://github.com/pczarnik/mnists
Classifier: Programming Language :: Python :: 3.9
Classifier: Programming Language :: Python :: 3.10
Classifier: Programming Language :: Python :: 3.11
Classifier: Programming Language :: Python :: 3.12
Classifier: Intended Audience :: Developers
Classifier: Intended Audience :: Science/Research
Classifier: License :: OSI Approved :: MIT License
Classifier: Operating System :: OS Independent
Requires-Python: >=3.9
License-File: LICENSE
Requires-Dist: numpy >=1.22
Requires-Dist: numpy >=1.23.2 ; python_version >= "3.11"
Requires-Dist: numpy >=1.26.0 ; python_version >= "3.12"
Provides-Extra: tqdm
Requires-Dist: tqdm ; extra == 'tqdm'
